VBBinaryLensing/VBBinaryLensing.cp311-win_amd64.pyd
VBBinaryLensing/__init__.py
VBBinaryLensing/data/ESPL.tbl
VBBinaryLensing/data/OB151212coords.txt
VBBinaryLensing/data/__init__.py
VBBinaryLensing/data/satellite1.txt
VBBinaryLensing/data/satellite2.txt
VBBinaryLensing/lib/VBBinaryLensingLibrary.cpp
VBBinaryLensing/lib/VBBinaryLensingLibrary.h
VBBinaryLensing/lib/python_bindings.cpp
VBBinaryLensing/tests/test_all.py
VBBinaryLensing/tests/test_magnification.py
VBBinaryLensing-3.7.0.dist-info/LICENSE
VBBinaryLensing-3.7.0.dist-info/METADATA
VBBinaryLensing-3.7.0.dist-info/WHEEL
VBBinaryLensing-3.7.0.dist-info/top_level.txt
VBBinaryLensing-3.7.0.dist-info/RECORD
