Metadata-Version: 2.1
Name: VBBinaryLensing
Version: 3.7.0
Summary: VBBinaryLensing is a tool for efficient computation in gravitational microlensing events using the advanced contour integration method, supporting single and binary lenses.
Home-page: http://astropy.org
Author: fran
Author-email: Valerio Bozza <valboz@sa.infn.it>, Fran Bartolić <fb90@st-andrews.ac.uk>, Etienne Bachelet <etibachelet@gmail.com>
License: GPL-3.0
Project-URL: Homepage, https://github.com/valboz/VBBinaryLensing
Project-URL: Documentation, https://www.fisica.unisa.it/gravitationastrophysics/VBBinaryLensing.htm
Keywords: Microlsening magnification and astrometry
Classifier: Development Status :: 5 - Production/Stable
Classifier: Intended Audience :: Developers
Classifier: Topic :: Software Development :: Build Tools
Classifier: License :: OSI Approved :: GNU General Public License v3 (GPLv3)
Classifier: Programming Language :: Python :: 3
Requires-Python: <4,>=3.6
License-File: LICENSE
Requires-Dist: numpy
Requires-Dist: pytest
